lab2mux8.vhdl
library IEEE;
use IEEE.STD_LOGIC_1164.ALL;

entity mux8 is
    Port (  I0 : in std_logic_vector (3 downto 0);
            I1 : in std_logic_vector (3 downto 0);
            I2 : in std_logic_vector (3 downto 0);
            I3 : in std_logic_vector (3 downto 0);
            I4 : in std_logic_vector (3 downto 0);
            I5 : in std_logic_vector (3 downto 0);
            I6 : in std_logic_vector (3 downto 0);
            I7 : in std_logic_vector (3 downto 0);
            S : in std_logic_vector (2 downto 0);
            Y : out std_logic_vector (3 downto 0));
end mux8;

architecture Behavioral of mux8 is

begin
    process(I0,I1,I2,I3,I4,I5,I6,I7,S) is
    begin
        case S is
            when "000" => Y <= I0;
            when "001" => Y <= I1;
            when "010" => Y <= I2;
            when "011" => Y <= I3;
            when "100" => Y <= I4;
            when "101" => Y <= I5;
            when "110" => Y <= I6;
            when others => Y <= I7;
        end case;
    end process;

end Behavioral;

lab2reg.vhdl
library ieee;
use ieee.std_logic_1164.all;

entity reg is
port(
  I: in std_logic_vector (3 downto 0); -- for loading
  clock: in std_logic; -- rising-edge triggering 
  enable: in std_logic; -- 0: don't do anything; 1: reg is enabled
  O: out std_logic_vector(3 downto 0) -- output the current register
);
end reg;

architecture behav of reg is

begin
    process(clock, enable)
    begin
      if rising_edge(clock) then
        if (enable = '1') then
          O<=I;
        end if;
      end if;
    end process;
end behav;

lab2demux.vhdl
library IEEE;
use IEEE.STD_LOGIC_1164.ALL;

entity demux8 is
    Port ( I : in std_logic;
           S : in std_logic_vector (2 downto 0);
           Y : out std_logic_vector (7 downto 0) := (others=>'0')
           );
end demux8;

architecture Behavioral of demux8 is

begin
    process(I,S) is
    begin
        -- Ensures that only one register is writing
        Y <= "00000000";
        case S is
            when "000" => Y(0) <= I;
            when "001" => Y(1) <= I;
            when "010" => Y(2) <= I;
            when "011" => Y(3) <= I;
            when "100" => Y(4) <= I;
            when "101" => Y(5) <= I;
            when "110" => Y(6) <= I;
            when others => Y(7) <= I;
        end case;
    end process;
end Behavioral;

lab2regb.vhdl
library ieee;
use ieee.std_logic_1164.all;

entity regb is
    Port (  i: in std_logic_vector (3 downto 0) := (others=>'0');
            s: in std_logic_vector (2 downto 0) := (others=>'0');
            clk, enable: in std_logic;
            o: out std_logic_vector (3 downto 0) := (others=>'0')
            );
end regb;

architecture behav of regb is
--  Declaration of the component that will be instantiated.


component demux8 is
    port (  I : in std_logic;
            S : in std_logic_vector (2 downto 0);
            Y : out std_logic_vector (7 downto 0) := (others=>'0')
            );
end component;

component reg is
    port(	
        I:	    in std_logic_vector (3 downto 0); -- for loading
        clock:	in std_logic; -- rising-edge triggering 
        enable:	in std_logic; -- 0: don't do anything; 1: reg is enabled
        O:	    out std_logic_vector(3 downto 0) := (others=>'0') -- output the current register content. 
    );
end component;

component mux8 is
    Port (  I0 : in std_logic_vector (3 downto 0);
            I1 : in std_logic_vector (3 downto 0);
            I2 : in std_logic_vector (3 downto 0);
            I3 : in std_logic_vector (3 downto 0);
            I4 : in std_logic_vector (3 downto 0);
            I5 : in std_logic_vector (3 downto 0);
            I6 : in std_logic_vector (3 downto 0);
            I7 : in std_logic_vector (3 downto 0);
            S : in std_logic_vector (2 downto 0);
            Y : out std_logic_vector (3 downto 0) := (others=>'0')
            );
end component;
    
-- Write enable wires that connect demux to registers
signal W : std_logic_vector (7 downto 0) := (others=>'0');
-- Read wires that connect registers to mux
signal R0 : std_logic_vector (3 downto 0) := (others=>'0');
signal R1 : std_logic_vector (3 downto 0) := (others=>'0');
signal R2 : std_logic_vector (3 downto 0) := (others=>'0');
signal R3 : std_logic_vector (3 downto 0) := (others=>'0');
signal R4 : std_logic_vector (3 downto 0) := (others=>'0');
signal R5 : std_logic_vector (3 downto 0) := (others=>'0');
signal R6 : std_logic_vector (3 downto 0) := (others=>'0');
signal R7 : std_logic_vector (3 downto 0) := (others=>'0');

begin
--  Component instantiation.
writedemux8: demux8 port map (  I => enable, S => s, Y(0) => W(0), Y(1) => W(1), Y(2) => W(2), 
                                Y(3) => W(3), Y(4) => W(4), Y(5) => W(5), Y(6) => W(6), Y(7) => W(7));
reg0: reg port map (i => i, clock => clk, enable => W(0), O => R0);
reg1: reg port map (i => i, clock => clk, enable => W(1), O => R1);
reg2: reg port map (i => i, clock => clk, enable => W(2), O => R2);
reg3: reg port map (i => i, clock => clk, enable => W(3), O => R3);
reg4: reg port map (i => i, clock => clk, enable => W(4), O => R4);
reg5: reg port map (i => i, clock => clk, enable => W(5), O => R5);
reg6: reg port map (i => i, clock => clk, enable => W(6), O => R6);
reg7: reg port map (i => i, clock => clk, enable => W(7), O => R7);
readmux8: mux8 port map (   I0 => R0, I1 => R1, I2 => R2, I3 => R3, I4 => R4, 
                            I5 => R5, I6 => R6, I7 => R7, S => s, Y => o);

end behav;

Part2/regbTB.vhdl
library ieee;
use ieee.std_logic_1164.all;

entity regb_tb is
end regb_tb;

architecture behav of regb_tb is
--  Declaration of the component that will be instantiated.

component regb is
    port (  I: in std_logic_vector (3 downto 0) := (others=>'0');
            S: in std_logic_vector (2 downto 0) := (others=>'0');
            clk, enable: in std_logic;
            O: out std_logic_vector (3 downto 0) := (others=>'0')
            );
end component;

-- Input and output signal declaration
signal i : std_logic_vector (3 downto 0) := (others=>'0');
signal s : std_logic_vector (2 downto 0) := (others=>'0');
signal clk, enable : std_logic;
signal o : std_logic_vector (3 downto 0) := (others=>'0');

begin
-- Component Instantiation
regbank : regb port map( I => i, S => s, clk => clk, enable => enable, O => o);

--  This process does the real job.
process
type pattern_type is record
--  The inputs of the reg.
	i : std_logic_vector (3 downto 0);
    s : std_logic_vector (2 downto 0);
	clock, enable : std_logic;
--  The expected outputs of the reg.
	o: std_logic_vector (3 downto 0);
end record;
--  The patterns to apply.
type pattern_array is array (natural range <>) of pattern_type;
constant patterns : pattern_array :=
(("0001", "000", '0', '1', "0000"),
("0001", "000", '1', '0', "0001"),
("1001", "000", '0', '1', "0001"),
("1001", "000", '1', '0', "1001"),
("1101", "001", '0', '1', "0000"), -- enable is delayed by 1 vector.
("1001", "001", '1', '0', "1001"), -- when enable is 1 for previous vector,
("1111", "001", '0', '1', "1001"), -- enable is seen as 1 for current vector.
("0101", "001", '1', '1', "0101"),
("0101", "010", '0', '1', "0000"),
("1101", "010", '1', '0', "1101"),
("1111", "010", '1', '1', "1101"),
("1110", "011", '0', '1', "0000"),
("1110", "011", '1', '0', "1110"),
("1010", "011", '1', '0', "1110"),
("0001", "100", '0', '1', "0000"),
("0101", "100", '1', '0', "0101"),
("1101", "100", '1', '1', "0101"),
("0111", "101", '0', '1', "0000"),
("1001", "101", '1', '0', "1001"),
("0001", "101", '1', '0', "1001"),
("0001", "110", '0', '1', "0000"),
("0001", "110", '1', '0', "0001"),
("0001", "111", '0', '1', "0000"),
("0011", "111", '1', '0', "0011"),
("0011", "111", '1', '1', "0011")
);
begin
    --  Check each pattern.
	for n in patterns'range loop
    --  Set the inputs.
		i <= patterns(n).i;
        s <= patterns(n).s;
		clk <= patterns(n).clock;
		enable <= patterns(n).enable;
    --  Wait for the results.
		wait for 1 ns;
    --  Check the outputs.
		assert o = patterns(n).o
		report "bad output value" severity error;
	end loop;
	assert false report "end of test" severity note;
    --  Wait forever; this will finish the simulation.
	wait;
end process;
end behav;

Part2/regb.vcd
$date
  Sun Apr 10 22:35:24 2022
$end
$version
  GHDL v0
$end
$timescale
  1 fs
$end
$scope module standard $end
$upscope $end
$scope module std_logic_1164 $end
$upscope $end
$scope module regb_tb $end
$var reg 4 ! i[3:0] $end
$var reg 3 " s[2:0] $end
$var reg 1 # clk $end
$var reg 1 $ enable $end
$var reg 4 % o[3:0] $end
$scope module regbank $end
$var reg 4 & i[3:0] $end
$var reg 3 ' s[2:0] $end
$var reg 1 ( clk $end
$var reg 1 ) enable $end
$var reg 4 * o[3:0] $end
$var reg 8 + w[7:0] $end
$var reg 4 , r0[3:0] $end
$var reg 4 - r1[3:0] $end
$var reg 4 . r2[3:0] $end
$var reg 4 / r3[3:0] $end
$var reg 4 0 r4[3:0] $end
$var reg 4 1 r5[3:0] $end
$var reg 4 2 r6[3:0] $end
$var reg 4 3 r7[3:0] $end
$scope module writedemux8 $end
$var reg 1 4 i $end
$var reg 3 5 s[2:0] $end
$var reg 8 6 y[7:0] $end
$upscope $end
$scope module reg0 $end
$var reg 4 7 i[3:0] $end
$var reg 1 8 clock $end
$var reg 1 9 enable $end
$var reg 4 : o[3:0] $end
$upscope $end
$scope module reg1 $end
$var reg 4 ; i[3:0] $end
$var reg 1 < clock $end
$var reg 1 = enable $end
$var reg 4 > o[3:0] $end
$upscope $end
$scope module reg2 $end
$var reg 4 ? i[3:0] $end
$var reg 1 @ clock $end
$var reg 1 A enable $end
$var reg 4 B o[3:0] $end
$upscope $end
$scope module reg3 $end
$var reg 4 C i[3:0] $end
$var reg 1 D clock $end
$var reg 1 E enable $end
$var reg 4 F o[3:0] $end
$upscope $end
$scope module reg4 $end
$var reg 4 G i[3:0] $end
$var reg 1 H clock $end
$var reg 1 I enable $end
$var reg 4 J o[3:0] $end
$upscope $end
$scope module reg5 $end
$var reg 4 K i[3:0] $end
$var reg 1 L clock $end
$var reg 1 M enable $end
$var reg 4 N o[3:0] $end
$upscope $end
$scope module reg6 $end
$var reg 4 O i[3:0] $end
$var reg 1 P clock $end
$var reg 1 Q enable $end
$var reg 4 R o[3:0] $end
$upscope $end
$scope module reg7 $end
$var reg 4 S i[3:0] $end
$var reg 1 T clock $end
$var reg 1 U enable $end
$var reg 4 V o[3:0] $end
$upscope $end
$scope module readmux8 $end
$var reg 4 W i0[3:0] $end
$var reg 4 X i1[3:0] $end
$var reg 4 Y i2[3:0] $end
$var reg 4 Z i3[3:0] $end
$var reg 4 [ i4[3:0] $end
$var reg 4 \ i5[3:0] $end
$var reg 4 ] i6[3:0] $end
$var reg 4 ^ i7[3:0] $end
$var reg 3 _ s[2:0] $end
$var reg 4 ` y[3:0] $end
$upscope $end
$upscope $end
$upscope $end
$enddefinitions $end
#0
b0001 !
b000 "
0#
1$
b0000 %
b0001 &
b000 '
0(
1)
b0000 *
b00000001 +
b0000 ,
b0000 -
b0000 .
b0000 /
b0000 0
b0000 1
b0000 2
b0000 3
14
b000 5
b00000001 6
b0001 7
08
19
b0000 :
b0001 ;
0<
0=
b0000 >
b0001 ?
0@
0A
b0000 B
b0001 C
0D
0E
b0000 F
b0001 G
0H
0I
b0000 J
b0001 K
0L
0M
b0000 N
b0001 O
0P
0Q
b0000 R
b0001 S
0T
0U
b0000 V
b0000 W
b0000 X
b0000 Y
b0000 Z
b0000 [
b0000 \
b0000 ]
b0000 ^
b000 _
b0000 `
#1000000
1#
0$
b0001 %
1(
0)
b0001 *
b00000000 +
b0001 ,
04
b00000000 6
18
09
b0001 :
1<
1@
1D
1H
1L
1P
1T
b0001 W
b0001 `
#2000000
b1001 !
0#
1$
b1001 &
0(
1)
b00000001 +
14
b00000001 6
b1001 7
08
19
b1001 ;
0<
b1001 ?
0@
b1001 C
0D
b1001 G
0H
b1001 K
0L
b1001 O
0P
b1001 S
0T
#3000000
1#
0$
b1001 %
1(
0)
b1001 *
b00000000 +
b1001 ,
04
b00000000 6
18
09
b1001 :
1<
1@
1D
1H
1L
1P
1T
b1001 W
b1001 `
#4000000
b1101 !
b001 "
0#
1$
b0000 %
b1101 &
b001 '
0(
1)
b0000 *
b00000010 +
14
b001 5
b00000010 6
b1101 7
08
b1101 ;
0<
1=
b1101 ?
0@
b1101 C
0D
b1101 G
0H
b1101 K
0L
b1101 O
0P
b1101 S
0T
b001 _
b0000 `
#5000000
b1001 !
1#
0$
b1001 %
b1001 &
1(
0)
b1001 *
b00000000 +
b1001 -
04
b00000000 6
b1001 7
18
b1001 ;
1<
0=
b1001 >
b1001 ?
1@
b1001 C
1D
b1001 G
1H
b1001 K
1L
b1001 O
1P
b1001 S
1T
b1001 X
b1001 `
#6000000
b1111 !
0#
1$
b1111 &
0(
1)
b00000010 +
14
b00000010 6
b1111 7
08
b1111 ;
0<
1=
b1111 ?
0@
b1111 C
0D
b1111 G
0H
b1111 K
0L
b1111 O
0P
b1111 S
0T
#7000000
b0101 !
1#
b0101 %
b0101 &
1(
b0101 *
b0101 -
b0101 7
18
b0101 ;
1<
b0101 >
b0101 ?
1@
b0101 C
1D
b0101 G
1H
b0101 K
1L
b0101 O
1P
b0101 S
1T
b0101 X
b0101 `
#8000000
b010 "
0#
b0000 %
b010 '
0(
b0000 *
b00000100 +
b010 5
b00000100 6
08
0<
0=
0@
1A
0D
0H
0L
0P
0T
b010 _
b0000 `
#9000000
b1101 !
1#
0$
b1101 %
b1101 &
1(
0)
b1101 *
b00000000 +
b1101 .
04
b00000000 6
b1101 7
18
b1101 ;
1<
b1101 ?
1@
0A
b1101 B
b1101 C
1D
b1101 G
1H
b1101 K
1L
b1101 O
1P
b1101 S
1T
b1101 Y
b1101 `
#10000000
b1111 !
1$
b1111 &
1)
b00000100 +
14
b00000100 6
b1111 7
b1111 ;
b1111 ?
1A
b1111 C
b1111 G
b1111 K
b1111 O
b1111 S
#11000000
b1110 !
b011 "
0#
b0000 %
b1110 &
b011 '
0(
b0000 *
b00001000 +
b011 5
b00001000 6
b1110 7
08
b1110 ;
0<
b1110 ?
0@
0A
b1110 C
0D
1E
b1110 G
0H
b1110 K
0L
b1110 O
0P
b1110 S
0T
b011 _
b0000 `
#12000000
1#
0$
b1110 %
1(
0)
b1110 *
b00000000 +
b1110 /
04
b00000000 6
18
1<
1@
1D
0E
b1110 F
1H
1L
1P
1T
b1110 Z
b1110 `
#13000000
b1010 !
b1010 &
b1010 7
b1010 ;
b1010 ?
b1010 C
b1010 G
b1010 K
b1010 O
b1010 S
#14000000
b0001 !
b100 "
0#
1$
b0000 %
b0001 &
b100 '
0(
1)
b0000 *
b00010000 +
14
b100 5
b00010000 6
b0001 7
08
b0001 ;
0<
b0001 ?
0@
b0001 C
0D
b0001 G
0H
1I
b0001 K
0L
b0001 O
0P
b0001 S
0T
b100 _
b0000 `
#15000000
b0101 !
1#
0$
b0101 %
b0101 &
1(
0)
b0101 *
b00000000 +
b0101 0
04
b00000000 6
b0101 7
18
b0101 ;
1<
b0101 ?
1@
b0101 C
1D
b0101 G
1H
0I
b0101 J
b0101 K
1L
b0101 O
1P
b0101 S
1T
b0101 [
b0101 `
#16000000
b1101 !
1$
b1101 &
1)
b00010000 +
14
b00010000 6
b1101 7
b1101 ;
b1101 ?
b1101 C
b1101 G
1I
b1101 K
b1101 O
b1101 S
#17000000
b0111 !
b101 "
0#
b0000 %
b0111 &
b101 '
0(
b0000 *
b00100000 +
b101 5
b00100000 6
b0111 7
08
b0111 ;
0<
b0111 ?
0@
b0111 C
0D
b0111 G
0H
0I
b0111 K
0L
1M
b0111 O
0P
b0111 S
0T
b101 _
b0000 `
#18000000
b1001 !
1#
0$
b1001 %
b1001 &
1(
0)
b1001 *
b00000000 +
b1001 1
04
b00000000 6
b1001 7
18
b1001 ;
1<
b1001 ?
1@
b1001 C
1D
b1001 G
1H
b1001 K
1L
0M
b1001 N
b1001 O
1P
b1001 S
1T
b1001 \
b1001 `
#19000000
b0001 !
b0001 &
b0001 7
b0001 ;
b0001 ?
b0001 C
b0001 G
b0001 K
b0001 O
b0001 S
#20000000
b110 "
0#
1$
b0000 %
b110 '
0(
1)
b0000 *
b01000000 +
14
b110 5
b01000000 6
08
0<
0@
0D
0H
0L
0P
1Q
0T
b110 _
b0000 `
#21000000
1#
0$
b0001 %
1(
0)
b0001 *
b00000000 +
b0001 2
04
b00000000 6
18
1<
1@
1D
1H
1L
1P
0Q
b0001 R
1T
b0001 ]
b0001 `
#22000000
b111 "
0#
1$
b0000 %
b111 '
0(
1)
b0000 *
b10000000 +
14
b111 5
b10000000 6
08
0<
0@
0D
0H
0L
0P
0T
1U
b111 _
b0000 `
#23000000
b0011 !
1#
0$
b0011 %
b0011 &
1(
0)
b0011 *
b00000000 +
b0011 3
04
b00000000 6
b0011 7
18
b0011 ;
1<
b0011 ?
1@
b0011 C
1D
b0011 G
1H
b0011 K
1L
b0011 O
1P
b0011 S
1T
0U
b0011 V
b0011 ^
b0011 `
#24000000
1$
1)
b10000000 +
14
b10000000 6
1U
